ssh_agent_setup/__init__.py
ssh_agent_setup/parse_agent_variables.py
ssh_agent_setup-2.0.1.dist-info/LICENSE
ssh_agent_setup-2.0.1.dist-info/WHEEL
ssh_agent_setup-2.0.1.dist-info/METADATA
ssh_agent_setup-2.0.1.dist-info/RECORD
