Metadata-Version: 2.1
Name: ssh-agent-setup
Version: 2.0.1
Summary: set up a working ssh-agent and add keys for any subprocesses you want to run
License: MIT
Author: Yoav Kleinberger
Author-email: haarcuba@gmail.com
Requires-Python: >=3.8,<4.0
Classifier: License :: OSI Approved :: MIT License
Classifier: Programming Language :: Python :: 3
Classifier: Programming Language :: Python :: 3.8
Classifier: Programming Language :: Python :: 3.9
Classifier: Programming Language :: Python :: 3.10
Classifier: Programming Language :: Python :: 3.11
